README.rst
setup.py
lib/pipsort/__init__.py
lib/pipsort/__main__.py
lib/pipsort/__version__.py
lib/pipsort/cli.py
lib/pipsort.egg-info/PKG-INFO
lib/pipsort.egg-info/SOURCES.txt
lib/pipsort.egg-info/dependency_links.txt
lib/pipsort.egg-info/entry_points.txt
lib/pipsort.egg-info/requires.txt
lib/pipsort.egg-info/top_level.txt
lib/pipsort/core/__init__.py
lib/pipsort/core/_config.py
lib/pipsort/core/_logger.py
test/test_cli.py
test/test_core.py