Metadata-Version: 1.0
Name: pipsort
Version: 0.1.1
Summary: Get pip search results sorted by version
Home-page: http://github.com/vinu76jsr/pipsort
Author: Vaibhav Mishra
Author-email: vinu76jsr@gmail.com
License: UNKNOWN
Platform: UNKNOWN
